matplotcli.py
matplotcli-0.2.0.post1.dist-info/LICENSE
matplotcli-0.2.0.post1.dist-info/METADATA
matplotcli-0.2.0.post1.dist-info/WHEEL
matplotcli-0.2.0.post1.dist-info/entry_points.txt
matplotcli-0.2.0.post1.dist-info/top_level.txt
matplotcli-0.2.0.post1.dist-info/RECORD
