Metadata-Version: 2.1
Name: matplotcli
Version: 0.2.0.post1
Summary: MatplotCLI: create matplotlib visualizations from the command-line
Home-page: https://github.com/dcmoura/matplotcli
Author: Daniel C. Moura
Author-email: daniel.c.moura@gmail.com
License: MIT license
Project-URL: Source, https://github.com/dcmoura/matplotcli
Keywords: visualization plots json
Platform: UNKNOWN
Classifier: Development Status :: 3 - Alpha
Classifier: Environment :: Console
Classifier: Intended Audience :: Developers
Classifier: License :: OSI Approved :: MIT License
Classifier: Natural Language :: English
Classifier: Programming Language :: Python
Classifier: Programming Language :: Python :: 2
Classifier: Programming Language :: Python :: 2.7
Classifier: Programming Language :: Python :: 3
Classifier: Programming Language :: Python :: 3.6
Classifier: Programming Language :: Python :: 3.7
Classifier: Programming Language :: Python :: 3.8
Classifier: Programming Language :: Python :: 3.9
Classifier: Topic :: Scientific/Engineering :: Visualization
Classifier: Topic :: Utilities
Requires-Python: >=2.7
License-File: LICENSE
Requires-Dist: matplotlib
Requires-Dist: numpy
